CHANGES.rst
LICENSE.txt
MANIFEST.in
README.rst
setup.py
styn/__init__.py
styn/_styn.py
styn.egg-info/PKG-INFO
styn.egg-info/SOURCES.txt
styn.egg-info/dependency_links.txt
styn.egg-info/entry_points.txt
styn.egg-info/top_level.txt