Metadata-Version: 1.0
Name: styn
Version: 1.0.0
Summary: Lightweight Python Build Tool for Celery Users.
Home-page: http://rags.github.com/pynt/
Author: Lenny Morayniss
Author-email: ldmoray@gmail.com
License: MIT License
Keywords: build
Platform: UNKNOWN
